patcher/__about__.py
patcher/__init__.py
patcher/cli.py
patcher/client/__init__.py
patcher/client/analyze.py
patcher/client/api_client.py
patcher/client/config_manager.py
patcher/client/plist_manager.py
patcher/client/report_manager.py
patcher/client/setup.py
patcher/client/token_manager.py
patcher/client/ui_manager.py
patcher/models/__init__.py
patcher/models/fragment.py
patcher/models/jamf_client.py
patcher/models/label.py
patcher/models/patch.py
patcher/models/token.py
patcher/models/ui.py
patcher/templates/analysis.html
patcher/utils/__init__.py
patcher/utils/animation.py
patcher/utils/data_manager.py
patcher/utils/decorators.py
patcher/utils/exceptions.py
patcher/utils/installomator.py
patcher/utils/logger.py
patcher/utils/pdf_report.py
patcherctl-2.2.0.dist-info/licenses/LICENSE.txt
patcherctl-2.2.0.dist-info/METADATA
patcherctl-2.2.0.dist-info/WHEEL
patcherctl-2.2.0.dist-info/entry_points.txt
patcherctl-2.2.0.dist-info/top_level.txt
patcherctl-2.2.0.dist-info/RECORD
