Metadata-Version: 2.4
Name: patcherctl
Version: 2.2.0
Summary: Fetch patch management data from Jamf Pro to generate comprehensive reports in both Excel and PDF formats
Author: Andrew Lerman, Chris Ball
Author-email: info@liquidzoo.io
Maintainer: Andrew Lerman, Chris Ball
License:                                  Apache License
Project-URL: Homepage, https://patcher.liquidzoo.io
Project-URL: Documentation, https://patcher.liquidzoo.io
Project-URL: Repository, https://github.com/liquidz00/Patcher
Project-URL: Issues, https://github.com/liquidz00/Patcher/issues/new?assignees=&labels=bug&projects=&template=issue.md&title=%5BISSUE%5D+Your+Issue+Title
Keywords: jamf,pro,jss,patch,macOS
Classifier: Development Status :: 3 - Alpha
Classifier: Programming Language :: Python :: 3.10
Classifier: Programming Language :: Python :: 3.11
Classifier: Programming Language :: Python :: 3.12
Classifier: Intended Audience :: System Administrators
Classifier: Intended Audience :: Information Technology
Classifier: Intended Audience :: Developers
Classifier: Topic :: Scientific/Engineering :: Information Analysis
Classifier: Topic :: Documentation
Classifier: License :: OSI Approved :: Apache Software License
Requires-Python: >=3.10
License-File: LICENSE.txt
Requires-Dist: asyncclick>=8.1.7.2
Requires-Dist: fpdf2>=2.7.8
Requires-Dist: keyring>=24.3.1
Requires-Dist: openpyxl>=3.1.2
Requires-Dist: pandas>=2.2.0
Requires-Dist: pyarrow>=15.0.0
Requires-Dist: pydantic>=2.7.4
Requires-Dist: rapidfuzz>=3.12.1
Provides-Extra: dev
Requires-Dist: black>=24.3.0; extra == "dev"
Requires-Dist: build; extra == "dev"
Requires-Dist: pytest>=8.2.2; extra == "dev"
Requires-Dist: pytest-asyncio>=0.23.5; extra == "dev"
Requires-Dist: pytest-cov>=4.0.0; extra == "dev"
Requires-Dist: pytest-mock>=3.14.0; extra == "dev"
Requires-Dist: ruff>=0.5.1; extra == "dev"
Provides-Extra: docs
Requires-Dist: autodoc-pydantic; extra == "docs"
Requires-Dist: myst-parser; extra == "docs"
Requires-Dist: pydata-sphinx-theme; extra == "docs"
Requires-Dist: sphinx>=7.3.7; extra == "docs"
Requires-Dist: sphinx-design; extra == "docs"
Requires-Dist: sphinx-copybutton; extra == "docs"
Requires-Dist: sphinx-togglebutton; extra == "docs"
Provides-Extra: all
Requires-Dist: patcherctl[dev]; extra == "all"
Requires-Dist: patcherctl[docs]; extra == "all"
Dynamic: license-file
